ais/__init__.py
ais/sentence.py
ais/wordnet.py
ais_wordnet-0.0.15.dist-info/METADATA
ais_wordnet-0.0.15.dist-info/WHEEL
ais_wordnet-0.0.15.dist-info/top_level.txt
ais_wordnet-0.0.15.dist-info/RECORD
