Metadata-Version: 2.1
Name: ais-wordnet
Version: 0.0.15
Summary: An interface for the wordnet
Home-page: https://github.com/minhdc/ais-wordnet
Author: Minh Dinh
Author-email: extreme45nm@gmail.com
License: UNKNOWN
Platform: UNKNOWN
Classifier: Programming Language :: Python :: 3
Classifier: License :: OSI Approved :: MIT License
Classifier: Operating System :: OS Independent
